gigagan/__init__.py
gigagan_pytorch/__init__.py
gigagan_pytorch/gigagan_pytorch.py
gigagan-0.0.1.dev0.dist-info/LICENSE
gigagan-0.0.1.dev0.dist-info/METADATA
gigagan-0.0.1.dev0.dist-info/WHEEL
gigagan-0.0.1.dev0.dist-info/top_level.txt
gigagan-0.0.1.dev0.dist-info/RECORD
